DeepFilterDataLoader-0.5.6.dist-info/METADATA
DeepFilterDataLoader-0.5.6.dist-info/WHEEL
DeepFilterDataLoader-0.5.6.dist-info/license_files/LICENSE
DeepFilterDataLoader-0.5.6.dist-info/license_files/LICENSE-APACHE
DeepFilterDataLoader-0.5.6.dist-info/license_files/LICENSE-MIT
libdfdata.libs/libaec-91f0ca0f.so.0
libdfdata.libs/libsz-0deeef7d.so.2
libdfdata.libs/libhdf5-b5e70f84.so.103
libdfdata/torch_dataloader.py
libdfdata/__init__.py
libdfdata/libdfdata.cpython-39-x86_64-linux-gnu.so
DeepFilterDataLoader-0.5.6.dist-info/RECORD
